Metadata-Version: 2.1
Name: fpstimer
Version: 0.0.1
Summary: A clock timer that provides sleep()-like features for maintaining a certain "frames per second" (FPS) framerate in Python 2 and 3.
Home-page: https://github.com/asweigart/fpstimer
Author: Al Sweigart
Author-email: al@inventwithpython.com
License: GPLv3+
Platform: UNKNOWN
Classifier: License :: OSI Approved :: GNU General Public License v3 or later (GPLv3+)
Classifier: Programming Language :: Python
Classifier: Programming Language :: Python :: 3
Classifier: Programming Language :: Python :: 3.4
Classifier: Programming Language :: Python :: 3.5
Classifier: Programming Language :: Python :: 3.6
Classifier: Programming Language :: Python :: 3.7
Classifier: Programming Language :: Python :: 3.8
